esi/__init__.py
esi/esi.py
esi_controls-0.0.1.dist-info/LICENSE
esi_controls-0.0.1.dist-info/METADATA
esi_controls-0.0.1.dist-info/WHEEL
esi_controls-0.0.1.dist-info/top_level.txt
esi_controls-0.0.1.dist-info/RECORD
