Metadata-Version: 2.1
Name: esi-controls
Version: 0.0.1
Summary: Python API client to the ESI Controls API for monitoring and controlling your thermostat.
Author-email: Josh Taylor <joshotaylor@gmail.com>
Project-URL: Homepage, https://github.com/josh-taylor/esi
Project-URL: Bug Tracker, https://github.com/josh-taylor/esi/issues
Classifier: Programming Language :: Python :: 3
Classifier: License :: OSI Approved :: MIT License
Classifier: Operating System :: OS Independent
Requires-Python: >=3.7
License-File: LICENSE
